LICENSE
MANIFEST.in
README.rst
requirements.txt
setup.py
disfork/__init__.py
disfork/__main__.py
disfork/abc.py
disfork/activity.py
disfork/appinfo.py
disfork/asset.py
disfork/audit_logs.py
disfork/backoff.py
disfork/channel.py
disfork/client.py
disfork/colour.py
disfork/components.py
disfork/context_managers.py
disfork/embeds.py
disfork/emoji.py
disfork/enums.py
disfork/errors.py
disfork/file.py
disfork/flags.py
disfork/gateway.py
disfork/guild.py
disfork/http.py
disfork/integrations.py
disfork/interactions.py
disfork/invite.py
disfork/iterators.py
disfork/member.py
disfork/mentions.py
disfork/message.py
disfork/mixins.py
disfork/object.py
disfork/oggparse.py
disfork/opus.py
disfork/partial_emoji.py
disfork/permissions.py
disfork/player.py
disfork/py.typed
disfork/raw_models.py
disfork/reaction.py
disfork/role.py
disfork/shard.py
disfork/stage_instance.py
disfork/state.py
disfork/sticker.py
disfork/team.py
disfork/template.py
disfork/threads.py
disfork/user.py
disfork/utils.py
disfork/voice_client.py
disfork/widget.py
disfork.egg-info/PKG-INFO
disfork.egg-info/SOURCES.txt
disfork.egg-info/dependency_links.txt
disfork.egg-info/requires.txt
disfork.egg-info/top_level.txt
disfork/bin/libopus-0.x64.dll
disfork/bin/libopus-0.x86.dll
disfork/ext/commands/__init__.py
disfork/ext/commands/_types.py
disfork/ext/commands/bot.py
disfork/ext/commands/cog.py
disfork/ext/commands/context.py
disfork/ext/commands/converter.py
disfork/ext/commands/cooldowns.py
disfork/ext/commands/core.py
disfork/ext/commands/errors.py
disfork/ext/commands/flags.py
disfork/ext/commands/help.py
disfork/ext/commands/view.py
disfork/ext/tasks/__init__.py
disfork/types/__init__.py
disfork/types/activity.py
disfork/types/appinfo.py
disfork/types/audit_log.py
disfork/types/channel.py
disfork/types/components.py
disfork/types/embed.py
disfork/types/emoji.py
disfork/types/gateway.py
disfork/types/guild.py
disfork/types/integration.py
disfork/types/interactions.py
disfork/types/invite.py
disfork/types/member.py
disfork/types/message.py
disfork/types/raw_models.py
disfork/types/role.py
disfork/types/snowflake.py
disfork/types/sticker.py
disfork/types/team.py
